[
  {
    "id": "CO-adams",
    "state": "Colorado",
    "stateCode": "CO",
    "county": "Adams County",
    "chairName": "TBD",
    "email": null,
    "phone": null,
    "electionDate": null,
    "source": "https://www.cologop.org/county-parties/",
    "lastVerified": "2025-12-28",
    "notes": "Needs verification"
  },
  {
    "id": "CO-alamosa",
    "state": "Colorado",
    "stateCode": "CO",
    "county": "Alamosa County",
    "chairName": "TBD",
    "email": null,
    "phone": null,
    "electionDate": null,
    "source": "https://www.cologop.org/county-parties/",
    "lastVerified": "2025-12-28",
    "notes": "Needs verification"
  },
  {
    "id": "CO-arapahoe",
    "state": "Colorado",
    "stateCode": "CO",
    "county": "Arapahoe County",
    "chairName": "TBD",
    "email": null,
    "phone": null,
    "electionDate": null,
    "source": "https://www.cologop.org/county-parties/",
    "lastVerified": "2025-12-28",
    "notes": "Needs verification"
  },
  {
    "id": "CO-archuleta",
    "state": "Colorado",
    "stateCode": "CO",
    "county": "Archuleta County",
    "chairName": "TBD",
    "email": null,
    "phone": null,
    "electionDate": null,
    "source": "https://www.cologop.org/county-parties/",
    "lastVerified": "2025-12-28",
    "notes": "Needs verification"
  },
  {
    "id": "CO-baca",
    "state": "Colorado",
    "stateCode": "CO",
    "county": "Baca County",
    "chairName": "TBD",
    "email": null,
    "phone": null,
    "electionDate": null,
    "source": "https://www.cologop.org/county-parties/",
    "lastVerified": "2025-12-28",
    "notes": "Needs verification"
  },
  {
    "id": "CO-bent",
    "state": "Colorado",
    "stateCode": "CO",
    "county": "Bent County",
    "chairName": "TBD",
    "email": null,
    "phone": null,
    "electionDate": null,
    "source": "https://www.cologop.org/county-parties/",
    "lastVerified": "2025-12-28",
    "notes": "Needs verification"
  },
  {
    "id": "CO-boulder",
    "state": "Colorado",
    "stateCode": "CO",
    "county": "Boulder County",
    "chairName": "TBD",
    "email": null,
    "phone": null,
    "electionDate": null,
    "source": "https://www.cologop.org/county-parties/",
    "lastVerified": "2025-12-28",
    "notes": "Needs verification"
  },
  {
    "id": "CO-broomfield",
    "state": "Colorado",
    "stateCode": "CO",
    "county": "Broomfield County",
    "chairName": "TBD",
    "email": null,
    "phone": null,
    "electionDate": null,
    "source": "https://www.cologop.org/county-parties/",
    "lastVerified": "2025-12-28",
    "notes": "Needs verification"
  },
  {
    "id": "CO-chaffee",
    "state": "Colorado",
    "stateCode": "CO",
    "county": "Chaffee County",
    "chairName": "TBD",
    "email": null,
    "phone": null,
    "electionDate": null,
    "source": "https://www.cologop.org/county-parties/",
    "lastVerified": "2025-12-28",
    "notes": "Needs verification"
  },
  {
    "id": "CO-cheyenne",
    "state": "Colorado",
    "stateCode": "CO",
    "county": "Cheyenne County",
    "chairName": "TBD",
    "email": null,
    "phone": null,
    "electionDate": null,
    "source": "https://www.cologop.org/county-parties/",
    "lastVerified": "2025-12-28",
    "notes": "Needs verification"
  },
  {
    "id": "CO-clear-creek",
    "state": "Colorado",
    "stateCode": "CO",
    "county": "Clear Creek County",
    "chairName": "TBD",
    "email": null,
    "phone": null,
    "electionDate": null,
    "source": "https://www.cologop.org/county-parties/",
    "lastVerified": "2025-12-28",
    "notes": "Needs verification"
  },
  {
    "id": "CO-conejos",
    "state": "Colorado",
    "stateCode": "CO",
    "county": "Conejos County",
    "chairName": "TBD",
    "email": null,
    "phone": null,
    "electionDate": null,
    "source": "https://www.cologop.org/county-parties/",
    "lastVerified": "2025-12-28",
    "notes": "Needs verification"
  },
  {
    "id": "CO-costilla",
    "state": "Colorado",
    "stateCode": "CO",
    "county": "Costilla County",
    "chairName": "TBD",
    "email": null,
    "phone": null,
    "electionDate": null,
    "source": "https://www.cologop.org/county-parties/",
    "lastVerified": "2025-12-28",
    "notes": "Needs verification"
  },
  {
    "id": "CO-crowley",
    "state": "Colorado",
    "stateCode": "CO",
    "county": "Crowley County",
    "chairName": "TBD",
    "email": null,
    "phone": null,
    "electionDate": null,
    "source": "https://www.cologop.org/county-parties/",
    "lastVerified": "2025-12-28",
    "notes": "Needs verification"
  },
  {
    "id": "CO-custer",
    "state": "Colorado",
    "stateCode": "CO",
    "county": "Custer County",
    "chairName": "TBD",
    "email": null,
    "phone": null,
    "electionDate": null,
    "source": "https://www.cologop.org/county-parties/",
    "lastVerified": "2025-12-28",
    "notes": "Needs verification"
  },
  {
    "id": "CO-delta",
    "state": "Colorado",
    "stateCode": "CO",
    "county": "Delta County",
    "chairName": "TBD",
    "email": null,
    "phone": null,
    "electionDate": null,
    "source": "https://www.cologop.org/county-parties/",
    "lastVerified": "2025-12-28",
    "notes": "Needs verification"
  },
  {
    "id": "CO-denver",
    "state": "Colorado",
    "stateCode": "CO",
    "county": "Denver County",
    "chairName": "TBD",
    "email": null,
    "phone": null,
    "electionDate": null,
    "source": "https://www.cologop.org/county-parties/",
    "lastVerified": "2025-12-28",
    "notes": "Needs verification"
  },
  {
    "id": "CO-dolores",
    "state": "Colorado",
    "stateCode": "CO",
    "county": "Dolores County",
    "chairName": "TBD",
    "email": null,
    "phone": null,
    "electionDate": null,
    "source": "https://www.cologop.org/county-parties/",
    "lastVerified": "2025-12-28",
    "notes": "Needs verification"
  },
  {
    "id": "CO-douglas",
    "state": "Colorado",
    "stateCode": "CO",
    "county": "Douglas County",
    "chairName": "TBD",
    "email": null,
    "phone": null,
    "electionDate": null,
    "source": "https://www.cologop.org/county-parties/",
    "lastVerified": "2025-12-28",
    "notes": "Needs verification"
  },
  {
    "id": "CO-eagle",
    "state": "Colorado",
    "stateCode": "CO",
    "county": "Eagle County",
    "chairName": "TBD",
    "email": null,
    "phone": null,
    "electionDate": null,
    "source": "https://www.cologop.org/county-parties/",
    "lastVerified": "2025-12-28",
    "notes": "Needs verification"
  },
  {
    "id": "CO-el-paso",
    "state": "Colorado",
    "stateCode": "CO",
    "county": "El Paso County",
    "chairName": "TBD",
    "email": null,
    "phone": null,
    "electionDate": null,
    "source": "https://www.cologop.org/county-parties/",
    "lastVerified": "2025-12-28",
    "notes": "Needs verification"
  },
  {
    "id": "CO-elbert",
    "state": "Colorado",
    "stateCode": "CO",
    "county": "Elbert County",
    "chairName": "TBD",
    "email": null,
    "phone": null,
    "electionDate": null,
    "source": "https://www.cologop.org/county-parties/",
    "lastVerified": "2025-12-28",
    "notes": "Needs verification"
  },
  {
    "id": "CO-fremont",
    "state": "Colorado",
    "stateCode": "CO",
    "county": "Fremont County",
    "chairName": "TBD",
    "email": null,
    "phone": null,
    "electionDate": null,
    "source": "https://www.cologop.org/county-parties/",
    "lastVerified": "2025-12-28",
    "notes": "Needs verification"
  },
  {
    "id": "CO-garfield",
    "state": "Colorado",
    "stateCode": "CO",
    "county": "Garfield County",
    "chairName": "TBD",
    "email": null,
    "phone": null,
    "electionDate": null,
    "source": "https://www.cologop.org/county-parties/",
    "lastVerified": "2025-12-28",
    "notes": "Needs verification"
  },
  {
    "id": "CO-gilpin",
    "state": "Colorado",
    "stateCode": "CO",
    "county": "Gilpin County",
    "chairName": "TBD",
    "email": null,
    "phone": null,
    "electionDate": null,
    "source": "https://www.cologop.org/county-parties/",
    "lastVerified": "2025-12-28",
    "notes": "Needs verification"
  },
  {
    "id": "CO-grand",
    "state": "Colorado",
    "stateCode": "CO",
    "county": "Grand County",
    "chairName": "TBD",
    "email": null,
    "phone": null,
    "electionDate": null,
    "source": "https://www.cologop.org/county-parties/",
    "lastVerified": "2025-12-28",
    "notes": "Needs verification"
  },
  {
    "id": "CO-gunnison",
    "state": "Colorado",
    "stateCode": "CO",
    "county": "Gunnison County",
    "chairName": "TBD",
    "email": null,
    "phone": null,
    "electionDate": null,
    "source": "https://www.cologop.org/county-parties/",
    "lastVerified": "2025-12-28",
    "notes": "Needs verification"
  },
  {
    "id": "CO-hinsdale",
    "state": "Colorado",
    "stateCode": "CO",
    "county": "Hinsdale County",
    "chairName": "TBD",
    "email": null,
    "phone": null,
    "electionDate": null,
    "source": "https://www.cologop.org/county-parties/",
    "lastVerified": "2025-12-28",
    "notes": "Needs verification"
  },
  {
    "id": "CO-huerfano",
    "state": "Colorado",
    "stateCode": "CO",
    "county": "Huerfano County",
    "chairName": "TBD",
    "email": null,
    "phone": null,
    "electionDate": null,
    "source": "https://www.cologop.org/county-parties/",
    "lastVerified": "2025-12-28",
    "notes": "Needs verification"
  },
  {
    "id": "CO-jackson",
    "state": "Colorado",
    "stateCode": "CO",
    "county": "Jackson County",
    "chairName": "TBD",
    "email": null,
    "phone": null,
    "electionDate": null,
    "source": "https://www.cologop.org/county-parties/",
    "lastVerified": "2025-12-28",
    "notes": "Needs verification"
  },
  {
    "id": "CO-jefferson",
    "state": "Colorado",
    "stateCode": "CO",
    "county": "Jefferson County",
    "chairName": "TBD",
    "email": null,
    "phone": null,
    "electionDate": null,
    "source": "https://www.cologop.org/county-parties/",
    "lastVerified": "2025-12-28",
    "notes": "Needs verification"
  },
  {
    "id": "CO-kiowa",
    "state": "Colorado",
    "stateCode": "CO",
    "county": "Kiowa County",
    "chairName": "TBD",
    "email": null,
    "phone": null,
    "electionDate": null,
    "source": "https://www.cologop.org/county-parties/",
    "lastVerified": "2025-12-28",
    "notes": "Needs verification"
  },
  {
    "id": "CO-kit-carson",
    "state": "Colorado",
    "stateCode": "CO",
    "county": "Kit Carson County",
    "chairName": "TBD",
    "email": null,
    "phone": null,
    "electionDate": null,
    "source": "https://www.cologop.org/county-parties/",
    "lastVerified": "2025-12-28",
    "notes": "Needs verification"
  },
  {
    "id": "CO-lake",
    "state": "Colorado",
    "stateCode": "CO",
    "county": "Lake County",
    "chairName": "TBD",
    "email": null,
    "phone": null,
    "electionDate": null,
    "source": "https://www.cologop.org/county-parties/",
    "lastVerified": "2025-12-28",
    "notes": "Needs verification"
  },
  {
    "id": "CO-la-plata",
    "state": "Colorado",
    "stateCode": "CO",
    "county": "La Plata County",
    "chairName": "TBD",
    "email": null,
    "phone": null,
    "electionDate": null,
    "source": "https://www.cologop.org/county-parties/",
    "lastVerified": "2025-12-28",
    "notes": "Needs verification"
  },
  {
    "id": "CO-larimer",
    "state": "Colorado",
    "stateCode": "CO",
    "county": "Larimer County",
    "chairName": "TBD",
    "email": null,
    "phone": null,
    "electionDate": null,
    "source": "https://www.cologop.org/county-parties/",
    "lastVerified": "2025-12-28",
    "notes": "Needs verification"
  },
  {
    "id": "CO-las-animas",
    "state": "Colorado",
    "stateCode": "CO",
    "county": "Las Animas County",
    "chairName": "TBD",
    "email": null,
    "phone": null,
    "electionDate": null,
    "source": "https://www.cologop.org/county-parties/",
    "lastVerified": "2025-12-28",
    "notes": "Needs verification"
  },
  {
    "id": "CO-lincoln",
    "state": "Colorado",
    "stateCode": "CO",
    "county": "Lincoln County",
    "chairName": "TBD",
    "email": null,
    "phone": null,
    "electionDate": null,
    "source": "https://www.cologop.org/county-parties/",
    "lastVerified": "2025-12-28",
    "notes": "Needs verification"
  },
  {
    "id": "CO-logan",
    "state": "Colorado",
    "stateCode": "CO",
    "county": "Logan County",
    "chairName": "TBD",
    "email": null,
    "phone": null,
    "electionDate": null,
    "source": "https://www.cologop.org/county-parties/",
    "lastVerified": "2025-12-28",
    "notes": "Needs verification"
  },
  {
    "id": "CO-mesa",
    "state": "Colorado",
    "stateCode": "CO",
    "county": "Mesa County",
    "chairName": "TBD",
    "email": null,
    "phone": null,
    "electionDate": null,
    "source": "https://www.cologop.org/county-parties/",
    "lastVerified": "2025-12-28",
    "notes": "Needs verification"
  },
  {
    "id": "CO-mineral",
    "state": "Colorado",
    "stateCode": "CO",
    "county": "Mineral County",
    "chairName": "TBD",
    "email": null,
    "phone": null,
    "electionDate": null,
    "source": "https://www.cologop.org/county-parties/",
    "lastVerified": "2025-12-28",
    "notes": "Needs verification"
  },
  {
    "id": "CO-moffat",
    "state": "Colorado",
    "stateCode": "CO",
    "county": "Moffat County",
    "chairName": "TBD",
    "email": null,
    "phone": null,
    "electionDate": null,
    "source": "https://www.cologop.org/county-parties/",
    "lastVerified": "2025-12-28",
    "notes": "Needs verification"
  },
  {
    "id": "CO-montezuma",
    "state": "Colorado",
    "stateCode": "CO",
    "county": "Montezuma County",
    "chairName": "TBD",
    "email": null,
    "phone": null,
    "electionDate": null,
    "source": "https://www.cologop.org/county-parties/",
    "lastVerified": "2025-12-28",
    "notes": "Needs verification"
  },
  {
    "id": "CO-montrose",
    "state": "Colorado",
    "stateCode": "CO",
    "county": "Montrose County",
    "chairName": "TBD",
    "email": null,
    "phone": null,
    "electionDate": null,
    "source": "https://www.cologop.org/county-parties/",
    "lastVerified": "2025-12-28",
    "notes": "Needs verification"
  },
  {
    "id": "CO-morgan",
    "state": "Colorado",
    "stateCode": "CO",
    "county": "Morgan County",
    "chairName": "TBD",
    "email": null,
    "phone": null,
    "electionDate": null,
    "source": "https://www.cologop.org/county-parties/",
    "lastVerified": "2025-12-28",
    "notes": "Needs verification"
  },
  {
    "id": "CO-otero",
    "state": "Colorado",
    "stateCode": "CO",
    "county": "Otero County",
    "chairName": "TBD",
    "email": null,
    "phone": null,
    "electionDate": null,
    "source": "https://www.cologop.org/county-parties/",
    "lastVerified": "2025-12-28",
    "notes": "Needs verification"
  },
  {
    "id": "CO-ouray",
    "state": "Colorado",
    "stateCode": "CO",
    "county": "Ouray County",
    "chairName": "TBD",
    "email": null,
    "phone": null,
    "electionDate": null,
    "source": "https://www.cologop.org/county-parties/",
    "lastVerified": "2025-12-28",
    "notes": "Needs verification"
  },
  {
    "id": "CO-park",
    "state": "Colorado",
    "stateCode": "CO",
    "county": "Park County",
    "chairName": "TBD",
    "email": null,
    "phone": null,
    "electionDate": null,
    "source": "https://www.cologop.org/county-parties/",
    "lastVerified": "2025-12-28",
    "notes": "Needs verification"
  },
  {
    "id": "CO-phillips",
    "state": "Colorado",
    "stateCode": "CO",
    "county": "Phillips County",
    "chairName": "TBD",
    "email": null,
    "phone": null,
    "electionDate": null,
    "source": "https://www.cologop.org/county-parties/",
    "lastVerified": "2025-12-28",
    "notes": "Needs verification"
  },
  {
    "id": "CO-pitkin",
    "state": "Colorado",
    "stateCode": "CO",
    "county": "Pitkin County",
    "chairName": "TBD",
    "email": null,
    "phone": null,
    "electionDate": null,
    "source": "https://www.cologop.org/county-parties/",
    "lastVerified": "2025-12-28",
    "notes": "Needs verification"
  },
  {
    "id": "CO-prowers",
    "state": "Colorado",
    "stateCode": "CO",
    "county": "Prowers County",
    "chairName": "TBD",
    "email": null,
    "phone": null,
    "electionDate": null,
    "source": "https://www.cologop.org/county-parties/",
    "lastVerified": "2025-12-28",
    "notes": "Needs verification"
  },
  {
    "id": "CO-pueblo",
    "state": "Colorado",
    "stateCode": "CO",
    "county": "Pueblo County",
    "chairName": "TBD",
    "email": null,
    "phone": null,
    "electionDate": null,
    "source": "https://www.cologop.org/county-parties/",
    "lastVerified": "2025-12-28",
    "notes": "Needs verification"
  },
  {
    "id": "CO-rio-blanco",
    "state": "Colorado",
    "stateCode": "CO",
    "county": "Rio Blanco County",
    "chairName": "TBD",
    "email": null,
    "phone": null,
    "electionDate": null,
    "source": "https://www.cologop.org/county-parties/",
    "lastVerified": "2025-12-28",
    "notes": "Needs verification"
  },
  {
    "id": "CO-rio-grande",
    "state": "Colorado",
    "stateCode": "CO",
    "county": "Rio Grande County",
    "chairName": "TBD",
    "email": null,
    "phone": null,
    "electionDate": null,
    "source": "https://www.cologop.org/county-parties/",
    "lastVerified": "2025-12-28",
    "notes": "Needs verification"
  },
  {
    "id": "CO-routt",
    "state": "Colorado",
    "stateCode": "CO",
    "county": "Routt County",
    "chairName": "TBD",
    "email": null,
    "phone": null,
    "electionDate": null,
    "source": "https://www.cologop.org/county-parties/",
    "lastVerified": "2025-12-28",
    "notes": "Needs verification"
  },
  {
    "id": "CO-saguache",
    "state": "Colorado",
    "stateCode": "CO",
    "county": "Saguache County",
    "chairName": "TBD",
    "email": null,
    "phone": null,
    "electionDate": null,
    "source": "https://www.cologop.org/county-parties/",
    "lastVerified": "2025-12-28",
    "notes": "Needs verification"
  },
  {
    "id": "CO-san-juan",
    "state": "Colorado",
    "stateCode": "CO",
    "county": "San Juan County",
    "chairName": "TBD",
    "email": null,
    "phone": null,
    "electionDate": null,
    "source": "https://www.cologop.org/county-parties/",
    "lastVerified": "2025-12-28",
    "notes": "Needs verification"
  },
  {
    "id": "CO-san-miguel",
    "state": "Colorado",
    "stateCode": "CO",
    "county": "San Miguel County",
    "chairName": "TBD",
    "email": null,
    "phone": null,
    "electionDate": null,
    "source": "https://www.cologop.org/county-parties/",
    "lastVerified": "2025-12-28",
    "notes": "Needs verification"
  },
  {
    "id": "CO-sedgwick",
    "state": "Colorado",
    "stateCode": "CO",
    "county": "Sedgwick County",
    "chairName": "TBD",
    "email": null,
    "phone": null,
    "electionDate": null,
    "source": "https://www.cologop.org/county-parties/",
    "lastVerified": "2025-12-28",
    "notes": "Needs verification"
  },
  {
    "id": "CO-summit",
    "state": "Colorado",
    "stateCode": "CO",
    "county": "Summit County",
    "chairName": "TBD",
    "email": null,
    "phone": null,
    "electionDate": null,
    "source": "https://www.cologop.org/county-parties/",
    "lastVerified": "2025-12-28",
    "notes": "Needs verification"
  },
  {
    "id": "CO-teller",
    "state": "Colorado",
    "stateCode": "CO",
    "county": "Teller County",
    "chairName": "TBD",
    "email": null,
    "phone": null,
    "electionDate": null,
    "source": "https://www.cologop.org/county-parties/",
    "lastVerified": "2025-12-28",
    "notes": "Needs verification"
  },
  {
    "id": "CO-washington",
    "state": "Colorado",
    "stateCode": "CO",
    "county": "Washington County",
    "chairName": "TBD",
    "email": null,
    "phone": null,
    "electionDate": null,
    "source": "https://www.cologop.org/county-parties/",
    "lastVerified": "2025-12-28",
    "notes": "Needs verification"
  },
  {
    "id": "CO-weld",
    "state": "Colorado",
    "stateCode": "CO",
    "county": "Weld County",
    "chairName": "TBD",
    "email": null,
    "phone": null,
    "electionDate": null,
    "source": "https://www.cologop.org/county-parties/",
    "lastVerified": "2025-12-28",
    "notes": "Needs verification"
  },
  {
    "id": "CO-yuma",
    "state": "Colorado",
    "stateCode": "CO",
    "county": "Yuma County",
    "chairName": "TBD",
    "email": null,
    "phone": null,
    "electionDate": null,
    "source": "https://www.cologop.org/county-parties/",
    "lastVerified": "2025-12-28",
    "notes": "Needs verification"
  }
]